[
  {
    "models": "Honda CR 250F",
    "from": 2025,
    "to": 2026
  },
  {
    "models": "Honda CRF 250RWE",
    "from": 2025,
    "to": 2026
  },
  {
    "models": "Honda CRF 250RX",
    "from": 2025,
    "to": 2026
  },
  {
    "models": "Honda CR 450F",
    "from": 2025,
    "to": 2026
  },
  {
    "models": "Honda CRF 450RWE",
    "from": 2025,
    "to": 2026
  },
  {
    "models": "Honda CRF 450RX",
    "from": 2025,
    "to": 2026
  },
  {
    "models": "TESTE",
    "from": 11,
    "to": 22
  }
]