[
  {
    "models": "Husqvarna 701 Enduro",
    "from": 2016,
    "to": 2018
  },
  {
    "models": "Husqvarna 701 Supermoto",
    "from": 2017,
    "to": 2018
  },
  {
    "models": "Husqvarna FC 450",
    "from": 2016,
    "to": 2021
  },
  {
    "models": "Husqvarna FC 450 Rockstar Edition",
    "from": 2018,
    "to": 2019
  },
  {
    "models": "Husqvarna FE 450",
    "from": 2017,
    "to": 2020
  },
  {
    "models": "Husqvarna FE 501",
    "from": 2017,
    "to": 2021
  },
  {
    "models": "Husqvarna FE 501s",
    "from": 2020,
    "to": 2021
  },
  {
    "models": "Husqvarna FS 450",
    "from": 2018,
    "to": 2020
  },
  {
    "models": "Husqvarna FX 450",
    "from": 2017,
    "to": 2020
  }
]